pyproject_migrator/__about__.py
pyproject_migrator/__init__.py
pyproject_migrator/__main__.py
pyproject_migrator/cli.py
pyproject_migrator/convert.py
pyproject_migrator/result.py
pyproject_migrator-1.1.1.dist-info/METADATA
pyproject_migrator-1.1.1.dist-info/WHEEL
pyproject_migrator-1.1.1.dist-info/entry_points.txt
pyproject_migrator-1.1.1.dist-info/licenses/LICENSE.txt
pyproject_migrator-1.1.1.dist-info/RECORD
