Metadata-Version: 2.1
Name: pyproject-migrator
Version: 1.1.1
Summary: Convert setup.cfg, etc. to pyproject.toml files
Project-URL: Documentation, https://github.com/akx/pyproject-migrator#readme
Project-URL: Issues, https://github.com/akx/pyproject-migrator/issues
Project-URL: Source, https://github.com/akx/pyproject-migrator
Author-email: Aarni Koskela <akx@iki.fi>
License-Expression: MIT
License-File: LICENSE.txt
Classifier: Development Status :: 4 - Beta
Classifier: Programming Language :: Python
Classifier: Programming Language :: Python :: 3.9
Classifier: Programming Language :: Python :: 3.10
Classifier: Programming Language :: Python :: 3.11
Classifier: Programming Language :: Python :: Implementation :: CPython
Classifier: Programming Language :: Python :: Implementation :: PyPy
Requires-Python: >=3.9
Requires-Dist: tomlkit~=0.11.0
